<?xml version="1.0"?>
<Results version="1.0">
<ReportNode type="testrun">
<ReportNode type="Action">
<ReportNode type="Step">
<Data>
    <Name>SystemUtil.Run "chrome.exe",1</Name>
    <StartTime>2022-07-07 07:01:45</StartTime>
    <Result>Done</Result>
    <Extension>
      <IconKey>c7761c963c66464195f6213689454e48</IconKey>
      <IsPlainTextNodeName>True</IsPlainTextNodeName>
    </Extension>
    <DeviceInfo />
  </Data>
</ReportNode>
<Data>
    <Name>Action1</Name>
    <Description />
    <StartTime>2022-07-07 07:01:43</StartTime>
    <Duration>2</Duration>
    <Result>Done</Result>
    <InputParameters />
    <Extension>
      <IconKey>64b88eb149a74d0cb8747fb70cecee20</IconKey>
      <IsPlainTextNodeName>True</IsPlainTextNodeName>
    </Extension>
  </Data>
</ReportNode>
<Data>
    <Name>AmazonProject</Name>
    <ToolName>Micro Focus UFT One</ToolName>
    <ToolVersion>2021</ToolVersion>
    <ToolVersionStringLiteral>2021</ToolVersionStringLiteral>
    <Description />
    <StartTime>2022-07-07 07:01:39</StartTime>
    <Duration>6</Duration>
    <Result>Done</Result>
    <InputParameters />
    <Extension>
      <IconKey>20c52c75267e465ca413efcc50e1e85b</IconKey>
      <IsPlainTextNodeName>True</IsPlainTextNodeName>
    </Extension>
    <Environment>
      <Timezone>+05:30:00</Timezone>
      <Locale>English (United States)</Locale>
      <User>ALCHEMYCLOUD\user239</User>
      <CpuInfo>Intel(R) Xeon(R) CPU E5-2673 v4 @ 2.30GHz</CpuInfo>
      <NumberOfCores>4</NumberOfCores>
      <TotalMemory>16383</TotalMemory>
      <HostName>alchemycloud.co.in\UFT-21</HostName>
      <OSInfo>Windows 10 1703 (x64)</OSInfo>
    </Environment>
    <TestedApplications />
    <Links>
      <Link type="DataTable" reference="Default.xlsx" displayname="Default Data Table" />
    </Links>
  </Data>
</ReportNode>
<GeneralInfo>
    <ResultName>Res345</ResultName>
    <RunStartTime>2022-07-07 07:01:39</RunStartTime>
    <Timezone>+05:30:00</Timezone>
    <OrchestrationToolName>Micro Focus UFT One</OrchestrationToolName>
    <OrchestrationToolVersion>2021</OrchestrationToolVersion>
    <OrchestrationToolVersionStringLiteral>2021</OrchestrationToolVersionStringLiteral>
  </GeneralInfo>
</Results>